pycont/ArclengthContinuation.py
pycont/BranchSwitching.py
pycont/Logger.py
pycont/Stability.py
pycont/Tangent.py
pycont/Types.py
pycont/__init__.py
pycont/_demo.py
pycont/continuation.py
pycont/exceptions.py
pycont/plotting.py
pycont/detection/__init__.py
pycont/detection/_bifurcation.py
pycont/detection/_fold.py
pycont/detection/_hopf.py
pycont/detection/base.py
pycont/detection/bifurcation.py
pycont/detection/fold.py
pycont/detection/hopf.py
pycont/detection/parammax.py
pycont/detection/parammin.py
pycont_lite-0.5.0.dist-info/licenses/LICENSE
pycont_lite-0.5.0.dist-info/METADATA
pycont_lite-0.5.0.dist-info/WHEEL
pycont_lite-0.5.0.dist-info/entry_points.txt
pycont_lite-0.5.0.dist-info/top_level.txt
pycont_lite-0.5.0.dist-info/RECORD
