Metadata-Version: 2.4
Name: pycont-lite
Version: 0.5.0
Summary: Lightweight matrix-free arclength continuation with bifurcation detection and branch switching.
Author-email: Hannes Vandecasteele <hannesvdc@gmail.com>
License: MIT License
Project-URL: Homepage, https://github.com/hannesvdc/PyCont-Lite
Project-URL: Documentation, https://github.com/hannesvdc/PyCont-Lite
Project-URL: Source, https://github.com/hannesvdc/PyCont-Lite
Requires-Python: >=3.10
License-File: LICENSE
Requires-Dist: numpy
Requires-Dist: scipy
Requires-Dist: matplotlib
Dynamic: license-file
